README.md
setup.py
openblu/__init__.py
openblu.egg-info/PKG-INFO
openblu.egg-info/SOURCES.txt
openblu.egg-info/dependency_links.txt
openblu.egg-info/top_level.txt
openblu/core/__init__.py
openblu/core/openblu.py
openblu/objects/__init__.py
openblu/objects/errors.py
openblu/objects/objects.py