Metadata-Version: 2.1
Name: openblu
Version: 1.0
Summary: Official Python 3 wrapper around the OpenBlu API
Home-page: https://github.com/intellivoid/OpenBlu-Python-Wrapper
Author: Intellivoid Technologies
Author-email: nocturn9x@intellivoid.net
License: UNKNOWN
Platform: UNKNOWN
Classifier: Programming Language :: Python :: 3
Classifier: Operating System :: OS Independent
Classifier: License :: OSI Approved :: Apache Software License
Requires-Python: >=3.6
